screen_watcher/main.py
screen_watcher/models.py
screen_watcher/screen-watcher.py
screen_watcher/slack.py
screen_watcher/utils.py
screen_watcher/version.py
screen_watcher-0.6.dist-info/METADATA
screen_watcher-0.6.dist-info/WHEEL
screen_watcher-0.6.dist-info/entry_points.txt
screen_watcher-0.6.dist-info/top_level.txt
screen_watcher-0.6.dist-info/RECORD
