Metadata-Version: 2.1
Name: screen-watcher
Version: 0.6
Summary: watching screen processes
Home-page: https://github.com/eunchong/screen-watcher
Author: eunchong
License: BSD
Platform: UNKNOWN
Requires-Dist: psutil (>=5.8.0)
Requires-Dist: slacker (>=0.12.0)
Requires-Dist: tabulate (>=0.8.9)
Requires-Dist: SQLAlchemy (>=1.4.25)
